{
  "$schema": "https://mintlify.com/docs.json",
  "name": "Pirson Dev Portfolio",
  "theme": "palm",
  "colors": {
    "primary": "#040404",
    "light": "#ffffff",
    "dark": "#040404"
  },
  "favicon": "/favicon.svg",
  "logo": {
    "light": "/logo-light.svg",
    "dark": "/logo-dark.svg"
  },
  "navbar": {
    "primary": {
      "type": "github",
      "href": "https://github.com/SrPirson/Portfolio"
    }
  },
  "footer": {
    "socials": {
      "github": "https://github.com/SrPirson/Portfolio",
      "linkedin": "https://www.linkedin.com/in/franciscocortespirson/",
      "website": "https://pirsondev.vercel.app"
    }
  },
  "navigation": {
    "groups": [
      {
        "group": "Overview",
        "pages": [
          "introduction",
          "features",
          "tech-stack"
        ]
      },
      {
        "group": "Getting Started",
        "pages": [
          "getting-started/installation",
          "getting-started/configuration",
          "getting-started/development"
        ]
      },
      {
        "group": "Components",
        "pages": [
          "components/overview",
          "components/navbar",
          "components/theme-switcher",
          "components/language-switcher",
          "components/timeline",
          "components/floating-dock"
        ]
      },
      {
        "group": "Customization",
        "pages": [
          "customization/styling",
          "customization/translations",
          "customization/content"
        ]
      },
      {
        "group": "Deployment",
        "pages": [
          "deployment/build",
          "deployment/vercel"
        ]
      }
    ]
  }
}
